refdata/__init__.py
refdata/base.py
refdata/config.py
refdata/db.py
refdata/error.py
refdata/version.py
refdata/cli/__init__.py
refdata/cli/base.py
refdata/cli/repo.py
refdata/cli/store.py
refdata/cli/util.py
refdata/dataset/__init__.py
refdata/dataset/base.py
refdata/dataset/consumer.py
refdata/dataset/csv_loader.py
refdata/dataset/json_loader.py
refdata/dataset/loader.py
refdata/repo/__init__.py
refdata/repo/loader.py
refdata/repo/manager.py
refdata/repo/schema.py
refdata/repo/schema.yaml
refdata/store/__init__.py
refdata/store/base.py
refdata/store/checksum.py
refdata-0.2.0.dist-info/LICENSE
refdata-0.2.0.dist-info/METADATA
refdata-0.2.0.dist-info/WHEEL
refdata-0.2.0.dist-info/entry_points.txt
refdata-0.2.0.dist-info/top_level.txt
refdata-0.2.0.dist-info/RECORD
