Metadata-Version: 2.1
Name: refdata
Version: 0.2.0
Summary: Library for accessing the Reference Data Repository
Home-page: https://github.com/VIDA-NYU/reference-data-repository
Author: Heiko Mueller
Author-email: heiko.muller@gmail.com
License: MIT
Keywords: data curation
Platform: UNKNOWN
Classifier: License :: OSI Approved :: MIT License
Classifier: Operating System :: OS Independent
Classifier: Programming Language :: Python :: 3
Classifier: Programming Language :: Python :: 3.7
Classifier: Programming Language :: Python :: 3.8
Classifier: Programming Language :: Python :: 3.9
Classifier: Programming Language :: Python
Requires-Dist: future
Requires-Dist: appdirs (>=1.4.4)
Requires-Dist: pandas (>=1.0.0)
Requires-Dist: python-dateutil
Requires-Dist: datasize (>=1.0.0)
Requires-Dist: pyyaml (>=5.1)
Requires-Dist: jsonschema
Requires-Dist: SQLAlchemy (>=1.3.18)
Requires-Dist: pooch (>=1.3.0)
Requires-Dist: requests
Requires-Dist: Click (>=7.0.0)
Requires-Dist: tableprint
Provides-Extra: dev
Requires-Dist: flake8 ; extra == 'dev'
Requires-Dist: python-language-server ; extra == 'dev'
Requires-Dist: mypy ; extra == 'dev'
Requires-Dist: pylint ; extra == 'dev'
Requires-Dist: pydocstyle ; extra == 'dev'
Requires-Dist: coverage (>=5.0) ; extra == 'dev'
Requires-Dist: pytest ; extra == 'dev'
Requires-Dist: pytest-cov ; extra == 'dev'
Provides-Extra: docs
Requires-Dist: Sphinx ; extra == 'docs'
Requires-Dist: sphinx-rtd-theme ; extra == 'docs'
Requires-Dist: sphinxcontrib-apidoc ; extra == 'docs'
Requires-Dist: jupyter-sphinx ; extra == 'docs'
Requires-Dist: nbshpinx ; extra == 'docs'
Requires-Dist: nbsphinx-link ; extra == 'docs'
Provides-Extra: tests
Requires-Dist: coverage (>=5.0) ; extra == 'tests'
Requires-Dist: pytest ; extra == 'tests'
Requires-Dist: pytest-cov ; extra == 'tests'
